dolphin_anty/__init__.py
dolphin_anty/exceptions.py
dolphin_anty/globals.py
dolphin_anty/types.py
dolphin_anty/utils.py
dolphin_anty-0.1.0.dist-info/LICENSE
dolphin_anty-0.1.0.dist-info/METADATA
dolphin_anty-0.1.0.dist-info/WHEEL
dolphin_anty-0.1.0.dist-info/RECORD
